veracodestats/__init__.py
veracodestats/api.py
veracodestats/api_hmac.py
veracodestats/data_manager.py
veracodestats/main.py
veracodestats/reports_manager.py
veracodestats/stats_manager.py
veracodestats/model/__init__.py
veracodestats/model/app.py
veracodestats/model/build.py
veracodestats/model/policy.py
veracodestats/model/sandbox.py
veracodestats-2018.4.4.dist-info/METADATA
veracodestats-2018.4.4.dist-info/RECORD
veracodestats-2018.4.4.dist-info/WHEEL
veracodestats-2018.4.4.dist-info/entry_points.txt
veracodestats-2018.4.4.dist-info/top_level.txt
